automated_selenium/__init__.py
automated_selenium/drivers/__init__.py
automated_selenium/drivers/undetected_driver.py
automated_selenium/pages/__init__.py
automated_selenium/pages/base_page.py
automated_selenium/resources/resources.py
automated_selenium-1.1.1.dist-info/LICENSE
automated_selenium-1.1.1.dist-info/METADATA
automated_selenium-1.1.1.dist-info/WHEEL
automated_selenium-1.1.1.dist-info/RECORD
