Metadata-Version: 2.1
Name: automated-selenium
Version: 1.1.1
Summary: Automated-Selenium is a Python library that provides a base page class designed to facilitate the implementation of the Page Object Model (POM) structure in Selenium-based test automation projects.
License: MIT
Author: Waqar Khan
Author-email: waqarkhan1252617@gmail.com
Requires-Python: >=3.8,<4.0
Classifier: License :: OSI Approved :: MIT License
Classifier: Programming Language :: Python :: 3
Classifier: Programming Language :: Python :: 3.8
Classifier: Programming Language :: Python :: 3.9
Classifier: Programming Language :: Python :: 3.10
Classifier: Programming Language :: Python :: 3.11
Requires-Dist: pyautogui (>=0.9.53,<0.10.0)
Requires-Dist: selenium (>=4.9.1,<5.0.0)
Requires-Dist: undetected-chromedriver (>=3.4.7,<4.0.0)
Requires-Dist: webdriver-manager (>=3.8.6,<4.0.0)
